<?xml version="1.0" encoding="UTF-8" standalone="yes"?><p:sldLayout xmlns:a="http://schemas.openxmlformats.org/drawingml/2006/main" xmlns:r="http://schemas.openxmlformats.org/officeDocument/2006/relationships" xmlns:mc="http://schemas.openxmlformats.org/markup-compatibility/2006" xmlns:mv="urn:schemas-microsoft-com:mac:vml" xmlns:p="http://schemas.openxmlformats.org/presentationml/2006/main" xmlns:c="http://schemas.openxmlformats.org/drawingml/2006/chart" xmlns:dgm="http://schemas.openxmlformats.org/drawingml/2006/diagram" xmlns:o="urn:schemas-microsoft-com:office:office" xmlns:v="urn:schemas-microsoft-com:vml" xmlns:pvml="urn:schemas-microsoft-com:office:powerpoint" xmlns:com="http://schemas.openxmlformats.org/drawingml/2006/compatibility" xmlns:p14="http://schemas.microsoft.com/office/powerpoint/2010/main" xmlns:p15="http://schemas.microsoft.com/office/powerpoint/2012/main" xmlns:ahyp="http://schemas.microsoft.com/office/drawing/2018/hyperlinkcolor" matchingName="Title and two columns" type="twoColTx"><p:cSld name="TITLE_AND_TWO_COLUMNS"><p:spTree><p:nvGrpSpPr><p:cNvPr id="25" name="Shape 25"/><p:cNvGrpSpPr/><p:nvPr/></p:nvGrpSpPr><p:grpSpPr><a:xfrm><a:off x="0" y="0"/><a:ext cx="0" cy="0"/><a:chOff x="0" y="0"/><a:chExt cx="0" cy="0"/></a:xfrm></p:grpSpPr><p:sp><p:nvSpPr><p:cNvPr id="26" name="Google Shape;26;p5"/><p:cNvSpPr txBox="1"/><p:nvPr><p:ph type="title"/></p:nvPr></p:nvSpPr><p:spPr><a:xfrm><a:off x="714850" y="445025"/><a:ext cx="7714200" cy="572700"/></a:xfrm><a:prstGeom prst="rect"><a:avLst/></a:prstGeom></p:spPr><p:txBody><a:bodyPr anchorCtr="0" anchor="t" bIns="91425" lIns="91425" spcFirstLastPara="1" rIns="91425" wrap="square" tIns="91425"><a:noAutofit/></a:bodyPr><a:lstStyle><a:lvl1pPr lvl="0"><a:spcBef><a:spcPts val="0"/></a:spcBef><a:spcAft><a:spcPts val="0"/></a:spcAft><a:buSzPts val="2700"/><a:buNone/><a:defRPr/></a:lvl1pPr><a:lvl2pPr lvl="1"><a:spcBef><a:spcPts val="0"/></a:spcBef><a:spcAft><a:spcPts val="0"/></a:spcAft><a:buSzPts val="2700"/><a:buNone/><a:defRPr/></a:lvl2pPr><a:lvl3pPr lvl="2"><a:spcBef><a:spcPts val="0"/></a:spcBef><a:spcAft><a:spcPts val="0"/></a:spcAft><a:buSzPts val="2700"/><a:buNone/><a:defRPr/></a:lvl3pPr><a:lvl4pPr lvl="3"><a:spcBef><a:spcPts val="0"/></a:spcBef><a:spcAft><a:spcPts val="0"/></a:spcAft><a:buSzPts val="2700"/><a:buNone/><a:defRPr/></a:lvl4pPr><a:lvl5pPr lvl="4"><a:spcBef><a:spcPts val="0"/></a:spcBef><a:spcAft><a:spcPts val="0"/></a:spcAft><a:buSzPts val="2700"/><a:buNone/><a:defRPr/></a:lvl5pPr><a:lvl6pPr lvl="5"><a:spcBef><a:spcPts val="0"/></a:spcBef><a:spcAft><a:spcPts val="0"/></a:spcAft><a:buSzPts val="2700"/><a:buNone/><a:defRPr/></a:lvl6pPr><a:lvl7pPr lvl="6"><a:spcBef><a:spcPts val="0"/></a:spcBef><a:spcAft><a:spcPts val="0"/></a:spcAft><a:buSzPts val="2700"/><a:buNone/><a:defRPr/></a:lvl7pPr><a:lvl8pPr lvl="7"><a:spcBef><a:spcPts val="0"/></a:spcBef><a:spcAft><a:spcPts val="0"/></a:spcAft><a:buSzPts val="2700"/><a:buNone/><a:defRPr/></a:lvl8pPr><a:lvl9pPr lvl="8"><a:spcBef><a:spcPts val="0"/></a:spcBef><a:spcAft><a:spcPts val="0"/></a:spcAft><a:buSzPts val="2700"/><a:buNone/><a:defRPr/></a:lvl9pPr></a:lstStyle><a:p/></p:txBody></p:sp><p:sp><p:nvSpPr><p:cNvPr id="27" name="Google Shape;27;p5"/><p:cNvSpPr txBox="1"/><p:nvPr><p:ph idx="1" type="body"/></p:nvPr></p:nvSpPr><p:spPr><a:xfrm><a:off x="311700" y="1152475"/><a:ext cx="3999900" cy="3416400"/></a:xfrm><a:prstGeom prst="rect"><a:avLst/></a:prstGeom></p:spPr><p:txBody><a:bodyPr anchorCtr="0" anchor="t" bIns="91425" lIns="91425" spcFirstLastPara="1" rIns="91425" wrap="square" tIns="91425"><a:noAutofit/></a:bodyPr><a:lstStyle><a:lvl1pPr indent="-317500" lvl="0" marL="457200"><a:spcBef><a:spcPts val="0"/></a:spcBef><a:spcAft><a:spcPts val="0"/></a:spcAft><a:buSzPts val="1400"/><a:buChar char="●"/><a:defRPr sz="1400"/></a:lvl1pPr><a:lvl2pPr indent="-304800" lvl="1" marL="914400"><a:spcBef><a:spcPts val="0"/></a:spcBef><a:spcAft><a:spcPts val="0"/></a:spcAft><a:buSzPts val="1200"/><a:buChar char="○"/><a:defRPr sz="1200"/></a:lvl2pPr><a:lvl3pPr indent="-304800" lvl="2" marL="1371600"><a:spcBef><a:spcPts val="0"/></a:spcBef><a:spcAft><a:spcPts val="0"/></a:spcAft><a:buSzPts val="1200"/><a:buChar char="■"/><a:defRPr sz="1200"/></a:lvl3pPr><a:lvl4pPr indent="-304800" lvl="3" marL="1828800"><a:spcBef><a:spcPts val="0"/></a:spcBef><a:spcAft><a:spcPts val="0"/></a:spcAft><a:buSzPts val="1200"/><a:buChar char="●"/><a:defRPr sz="1200"/></a:lvl4pPr><a:lvl5pPr indent="-304800" lvl="4" marL="2286000"><a:spcBef><a:spcPts val="0"/></a:spcBef><a:spcAft><a:spcPts val="0"/></a:spcAft><a:buSzPts val="1200"/><a:buChar char="○"/><a:defRPr sz="1200"/></a:lvl5pPr><a:lvl6pPr indent="-304800" lvl="5" marL="2743200"><a:spcBef><a:spcPts val="0"/></a:spcBef><a:spcAft><a:spcPts val="0"/></a:spcAft><a:buSzPts val="1200"/><a:buChar char="■"/><a:defRPr sz="1200"/></a:lvl6pPr><a:lvl7pPr indent="-304800" lvl="6" marL="3200400"><a:spcBef><a:spcPts val="0"/></a:spcBef><a:spcAft><a:spcPts val="0"/></a:spcAft><a:buSzPts val="1200"/><a:buChar char="●"/><a:defRPr sz="1200"/></a:lvl7pPr><a:lvl8pPr indent="-304800" lvl="7" marL="3657600"><a:spcBef><a:spcPts val="0"/></a:spcBef><a:spcAft><a:spcPts val="0"/></a:spcAft><a:buSzPts val="1200"/><a:buChar char="○"/><a:defRPr sz="1200"/></a:lvl8pPr><a:lvl9pPr indent="-304800" lvl="8" marL="4114800"><a:spcBef><a:spcPts val="0"/></a:spcBef><a:spcAft><a:spcPts val="0"/></a:spcAft><a:buSzPts val="1200"/><a:buChar char="■"/><a:defRPr sz="1200"/></a:lvl9pPr></a:lstStyle><a:p/></p:txBody></p:sp><p:sp><p:nvSpPr><p:cNvPr id="28" name="Google Shape;28;p5"/><p:cNvSpPr txBox="1"/><p:nvPr><p:ph idx="2" type="body"/></p:nvPr></p:nvSpPr><p:spPr><a:xfrm><a:off x="4832400" y="1152475"/><a:ext cx="3999900" cy="3416400"/></a:xfrm><a:prstGeom prst="rect"><a:avLst/></a:prstGeom></p:spPr><p:txBody><a:bodyPr anchorCtr="0" anchor="t" bIns="91425" lIns="91425" spcFirstLastPara="1" rIns="91425" wrap="square" tIns="91425"><a:noAutofit/></a:bodyPr><a:lstStyle><a:lvl1pPr indent="-317500" lvl="0" marL="457200"><a:spcBef><a:spcPts val="0"/></a:spcBef><a:spcAft><a:spcPts val="0"/></a:spcAft><a:buSzPts val="1400"/><a:buChar char="●"/><a:defRPr sz="1400"/></a:lvl1pPr><a:lvl2pPr indent="-304800" lvl="1" marL="914400"><a:spcBef><a:spcPts val="0"/></a:spcBef><a:spcAft><a:spcPts val="0"/></a:spcAft><a:buSzPts val="1200"/><a:buChar char="○"/><a:defRPr sz="1200"/></a:lvl2pPr><a:lvl3pPr indent="-304800" lvl="2" marL="1371600"><a:spcBef><a:spcPts val="0"/></a:spcBef><a:spcAft><a:spcPts val="0"/></a:spcAft><a:buSzPts val="1200"/><a:buChar char="■"/><a:defRPr sz="1200"/></a:lvl3pPr><a:lvl4pPr indent="-304800" lvl="3" marL="1828800"><a:spcBef><a:spcPts val="0"/></a:spcBef><a:spcAft><a:spcPts val="0"/></a:spcAft><a:buSzPts val="1200"/><a:buChar char="●"/><a:defRPr sz="1200"/></a:lvl4pPr><a:lvl5pPr indent="-304800" lvl="4" marL="2286000"><a:spcBef><a:spcPts val="0"/></a:spcBef><a:spcAft><a:spcPts val="0"/></a:spcAft><a:buSzPts val="1200"/><a:buChar char="○"/><a:defRPr sz="1200"/></a:lvl5pPr><a:lvl6pPr indent="-304800" lvl="5" marL="2743200"><a:spcBef><a:spcPts val="0"/></a:spcBef><a:spcAft><a:spcPts val="0"/></a:spcAft><a:buSzPts val="1200"/><a:buChar char="■"/><a:defRPr sz="1200"/></a:lvl6pPr><a:lvl7pPr indent="-304800" lvl="6" marL="3200400"><a:spcBef><a:spcPts val="0"/></a:spcBef><a:spcAft><a:spcPts val="0"/></a:spcAft><a:buSzPts val="1200"/><a:buChar char="●"/><a:defRPr sz="1200"/></a:lvl7pPr><a:lvl8pPr indent="-304800" lvl="7" marL="3657600"><a:spcBef><a:spcPts val="0"/></a:spcBef><a:spcAft><a:spcPts val="0"/></a:spcAft><a:buSzPts val="1200"/><a:buChar char="○"/><a:defRPr sz="1200"/></a:lvl8pPr><a:lvl9pPr indent="-304800" lvl="8" marL="4114800"><a:spcBef><a:spcPts val="0"/></a:spcBef><a:spcAft><a:spcPts val="0"/></a:spcAft><a:buSzPts val="1200"/><a:buChar char="■"/><a:defRPr sz="1200"/></a:lvl9pPr></a:lstStyle><a:p/></p:txBody></p:sp><p:sp><p:nvSpPr><p:cNvPr id="29" name="Google Shape;29;p5"/><p:cNvSpPr/><p:nvPr/></p:nvSpPr><p:spPr><a:xfrm flipH="1" rot="-5645395"><a:off x="8114913" y="3184813"/><a:ext cx="1774547" cy="1787280"/></a:xfrm><a:custGeom><a:rect b="b" l="l" r="r" t="t"/><a:pathLst><a:path extrusionOk="0" h="45027" w="46789"><a:moveTo><a:pt x="40604" y="44701"/></a:moveTo><a:lnTo><a:pt x="2197" y="34312"/></a:lnTo><a:cubicBezTo><a:pt x="407" y="33851"/><a:pt x="0" y="31464"/><a:pt x="1519" y="30380"/></a:cubicBezTo><a:lnTo><a:pt x="43181" y="1086"/></a:lnTo><a:cubicBezTo><a:pt x="44700" y="1"/><a:pt x="46789" y="1221"/><a:pt x="46626" y="3066"/></a:cubicBezTo><a:lnTo><a:pt x="43371" y="42721"/></a:lnTo><a:cubicBezTo><a:pt x="43235" y="44104"/><a:pt x="41934" y="45026"/><a:pt x="40604" y="44701"/></a:cubicBezTo><a:close/></a:path></a:pathLst></a:custGeom><a:solidFill><a:schemeClr val="lt2"/></a:solidFill><a:ln><a:noFill/></a:ln></p:spPr><p:txBody><a:bodyPr anchorCtr="0" anchor="ctr" bIns="91425" lIns="91425" spcFirstLastPara="1" rIns="91425" wrap="square" tIns="91425"><a:noAutofit/></a:bodyPr><a:lstStyle/><a:p><a:pPr indent="0" lvl="0" marL="0" rtl="0" algn="l"><a:spcBef><a:spcPts val="0"/></a:spcBef><a:spcAft><a:spcPts val="0"/></a:spcAft><a:buNone/></a:pPr><a:r><a:t></a:t></a:r><a:endParaRPr/></a:p></p:txBody></p:sp><p:sp><p:nvSpPr><p:cNvPr id="30" name="Google Shape;30;p5"/><p:cNvSpPr/><p:nvPr/></p:nvSpPr><p:spPr><a:xfrm><a:off x="5706299" y="4698075"/><a:ext cx="3099379" cy="125829"/></a:xfrm><a:custGeom><a:rect b="b" l="l" r="r" t="t"/><a:pathLst><a:path extrusionOk="0" h="7243" w="43644"><a:moveTo><a:pt x="42694" y="7242"/></a:moveTo><a:lnTo><a:pt x="950" y="7242"/></a:lnTo><a:cubicBezTo><a:pt x="408" y="7242"/><a:pt x="1" y="6808"/><a:pt x="1" y="6293"/></a:cubicBezTo><a:lnTo><a:pt x="1" y="950"/></a:lnTo><a:cubicBezTo><a:pt x="1" y="407"/><a:pt x="462" y="0"/><a:pt x="950" y="0"/></a:cubicBezTo><a:lnTo><a:pt x="42694" y="0"/></a:lnTo><a:cubicBezTo><a:pt x="43236" y="0"/><a:pt x="43643" y="434"/><a:pt x="43643" y="950"/></a:cubicBezTo><a:lnTo><a:pt x="43643" y="6293"/></a:lnTo><a:cubicBezTo><a:pt x="43643" y="6808"/><a:pt x="43209" y="7242"/><a:pt x="42694" y="7242"/></a:cubicBezTo><a:close/></a:path></a:pathLst></a:custGeom><a:solidFill><a:schemeClr val="accent1"/></a:solidFill><a:ln><a:noFill/></a:ln></p:spPr><p:txBody><a:bodyPr anchorCtr="0" anchor="ctr" bIns="91425" lIns="91425" spcFirstLastPara="1" rIns="91425" wrap="square" tIns="91425"><a:noAutofit/></a:bodyPr><a:lstStyle/><a:p><a:pPr indent="0" lvl="0" marL="0" rtl="0" algn="l"><a:spcBef><a:spcPts val="0"/></a:spcBef><a:spcAft><a:spcPts val="0"/></a:spcAft><a:buNone/></a:pPr><a:r><a:t></a:t></a:r><a:endParaRPr/></a:p></p:txBody></p:sp><p:sp><p:nvSpPr><p:cNvPr id="31" name="Google Shape;31;p5"/><p:cNvSpPr/><p:nvPr/></p:nvSpPr><p:spPr><a:xfrm rot="5400000"><a:off x="-784102" y="2351592"/><a:ext cx="1858542" cy="929271"/></a:xfrm><a:custGeom><a:rect b="b" l="l" r="r" t="t"/><a:pathLst><a:path extrusionOk="0" h="11121" w="22242"><a:moveTo><a:pt x="3797" y="11121"/></a:moveTo><a:lnTo><a:pt x="678" y="11121"/></a:lnTo><a:cubicBezTo><a:pt x="298" y="11121"/><a:pt x="0" y="10823"/><a:pt x="0" y="10443"/></a:cubicBezTo><a:lnTo><a:pt x="0" y="678"/></a:lnTo><a:cubicBezTo><a:pt x="0" y="299"/><a:pt x="298" y="0"/><a:pt x="678" y="0"/></a:cubicBezTo><a:lnTo><a:pt x="21564" y="0"/></a:lnTo><a:cubicBezTo><a:pt x="21943" y="0"/><a:pt x="22242" y="299"/><a:pt x="22242" y="678"/></a:cubicBezTo><a:lnTo><a:pt x="22242" y="10443"/></a:lnTo><a:cubicBezTo><a:pt x="22242" y="10823"/><a:pt x="21943" y="11121"/><a:pt x="21564" y="11121"/></a:cubicBezTo><a:lnTo><a:pt x="18444" y="11121"/></a:lnTo><a:cubicBezTo><a:pt x="18092" y="11121"/><a:pt x="17793" y="10850"/><a:pt x="17766" y="10497"/></a:cubicBezTo><a:cubicBezTo><a:pt x="17468" y="7107"/><a:pt x="14620" y="4449"/><a:pt x="11121" y="4449"/></a:cubicBezTo><a:cubicBezTo><a:pt x="7676" y="4449"/><a:pt x="4774" y="7107"/><a:pt x="4476" y="10497"/></a:cubicBezTo><a:cubicBezTo><a:pt x="4448" y="10850"/><a:pt x="4150" y="11121"/><a:pt x="3797" y="11121"/></a:cubicBezTo><a:close/></a:path></a:pathLst></a:custGeom><a:solidFill><a:schemeClr val="accent2"/></a:solidFill><a:ln><a:noFill/></a:ln></p:spPr><p:txBody><a:bodyPr anchorCtr="0" anchor="ctr" bIns="91425" lIns="91425" spcFirstLastPara="1" rIns="91425" wrap="square" tIns="91425"><a:noAutofit/></a:bodyPr><a:lstStyle/><a:p><a:pPr indent="0" lvl="0" marL="0" rtl="0" algn="l"><a:spcBef><a:spcPts val="0"/></a:spcBef><a:spcAft><a:spcPts val="0"/></a:spcAft><a:buNone/></a:pPr><a:r><a:t></a:t></a:r><a:endParaRPr/></a:p></p:txBody></p:sp></p:spTree></p:cSld><p:clrMapOvr><a:masterClrMapping/></p:clrMapOvr></p:sldLayout>